turtlel/__init__.py
turtlel/main.py
turtlel-0.0.1.dist-info/METADATA
turtlel-0.0.1.dist-info/WHEEL
turtlel-0.0.1.dist-info/licenses/LICENSE
turtlel-0.0.1.dist-info/RECORD
