Metadata-Version: 2.4
Name: turtlel
Version: 0.0.1
Summary: refd1312
Author-email: dffff <dfc1323@gmail.com>
License-File: LICENSE
Classifier: License :: OSI Approved :: MIT License
Classifier: Operating System :: OS Independent
Classifier: Programming Language :: Python :: 3
Requires-Python: >=3.10.0
